{
  "version": 1,
  "name": "optimus",
  "processing": {
    "cell_size": 128,
    "fit_scale": 0.8,
    "trim_border": 4,
    "edge_clean_depth": 3,
    "align": "feet",
    "shared_scale": false,
    "scale_strategy": "preserve",
    "component_mode": "largest",
    "component_padding": 0,
    "min_component_area": 3,
    "edge_touch_margin": 0
  },
  "output_origin": [
    64.0,
    116
  ],
  "reference": {
    "target": "npc",
    "mode": "sheet",
    "rows": 2,
    "cols": 3,
    "body_scale_mean": 0.3814253656451167,
    "body_scale_cv": 0.013993856028834354,
    "anchor_y_mean": 0.8019179894179894
  },
  "qc": {
    "max_body_scale_drift": 0.1
  }
}